simdata/__init__.py
simdata/sim.py
simdata-0.0.6.dist-info/LICENSE
simdata-0.0.6.dist-info/METADATA
simdata-0.0.6.dist-info/WHEEL
simdata-0.0.6.dist-info/RECORD
