Metadata-Version: 2.1
Name: simdata
Version: 0.0.6
Summary: 
Author: dm
Author-email: git@defend.sh
Requires-Python: >=3.12,<4.0
Classifier: Programming Language :: Python :: 3
Classifier: Programming Language :: Python :: 3.12
Classifier: Programming Language :: Python :: 3.13
Requires-Dist: numpy (>=2.1.3,<3.0.0)
Requires-Dist: polars (>=1.31.0,<2.0.0)
Requires-Dist: pydantic (>=2.9.2,<3.0.0)
